futsu/__init__.py
futsu/csv.py
futsu/fs.py
futsu/hash.py
futsu/json.py
futsu/lazy_import.py
futsu/storage.py
futsu/aws/__init__.py
futsu/aws/s3.py
futsu/aws/test/__init__.py
futsu/aws/test/test_storage.py
futsu/gcp/__init__.py
futsu/gcp/storage.py
futsu/gcp/test/__init__.py
futsu/gcp/test/test_storage.py
futsu/test/__init__.py
futsu/test/test_csv.py
futsu/test/test_fs.py
futsu/test/test_hash.py
futsu/test/test_json.py
futsu/test/test_lazy_import.py
futsu/test/test_storage.py
futsu/test/test_storage_20200913.py
futsu-0.0.35.dist-info/COPYING
futsu-0.0.35.dist-info/LICENSE
futsu-0.0.35.dist-info/METADATA
futsu-0.0.35.dist-info/WHEEL
futsu-0.0.35.dist-info/top_level.txt
futsu-0.0.35.dist-info/RECORD
