Metadata-Version: 2.1
Name: futsu
Version: 0.0.35
Summary: Very reusable python code
Home-page: https://github.com/luzi82/py.futsu
Author: Luzi Leung
Author-email: luzi82@gmail.com
Classifier: Programming Language :: Python :: 3
Classifier: License :: Public Domain
Classifier: Operating System :: OS Independent
Requires-Python: >=3
License-File: LICENSE
License-File: COPYING
